README.rst
setup.py
info_generators/__init__.py
info_generators/address_generator.py
info_generators/area_generator.py
info_generators/bank_generator.py
info_generators/birthday_generator.py
info_generators/email_generator.py
info_generators/gabc_generator.py
info_generators/identify_generator.py
info_generators/mobile_generator.py
info_generators/name_generator.py
info_generators/person_generator.py
info_generators.egg-info/PKG-INFO
info_generators.egg-info/SOURCES.txt
info_generators.egg-info/dependency_links.txt
info_generators.egg-info/requires.txt
info_generators.egg-info/top_level.txt
info_generators/consts/area.txt
info_generators/consts/city.txt
info_generators/consts/codes.txt